iinit/__init__.py
iinit/_version.py
iinit-2.1.0.data/data/share/jupyter/labextensions/iinit/package.json
iinit-2.1.0.data/data/share/jupyter/labextensions/iinit/static/509.50e057061a761f77b028.js
iinit-2.1.0.data/data/share/jupyter/labextensions/iinit/static/728.7ba0c69ed6e62ccfd555.js
iinit-2.1.0.data/data/share/jupyter/labextensions/iinit/static/remoteEntry.0f7ef8af334620880dfc.js
iinit-2.1.0.data/data/share/jupyter/labextensions/iinit/static/style.js
iinit-2.1.0.data/data/share/jupyter/labextensions/iinit/static/third-party-licenses.json
iinit-2.1.0.data/data/share/jupyter/labextensions/iinit/install.json
iinit-2.1.0.dist-info/METADATA
iinit-2.1.0.dist-info/WHEEL
iinit-2.1.0.dist-info/licenses/LICENSE
iinit-2.1.0.dist-info/RECORD
