Metadata-Version: 2.3
Name: iinit
Version: 2.1.0
Summary: A jupyter lab/notebook front-end extension for running/executing cells on kernel start-up
Project-URL: Homepage, https://github.com/lambdadotjoburg/iinit
Project-URL: Bug Tracker, https://github.com/lambdadotjoburg/iinit/issues
Project-URL: Repository, https://github.com/lambdadotjoburg/iinit.git
Author-email: lambda <lambdadotjoburg@gmail.com>
License: BSD 3-Clause License
License-File: LICENSE
Classifier: Framework :: Jupyter
Classifier: Framework :: Jupyter :: JupyterLab
Classifier: Framework :: Jupyter :: JupyterLab :: 4
Classifier: Framework :: Jupyter :: JupyterLab :: Extensions
Classifier: Framework :: Jupyter :: JupyterLab :: Extensions :: Prebuilt
Classifier: License :: OSI Approved :: BSD License
Classifier: Programming Language :: Python
Classifier: Programming Language :: Python :: 3
Classifier: Programming Language :: Python :: 3.8
Classifier: Programming Language :: Python :: 3.9
Classifier: Programming Language :: Python :: 3.10
Classifier: Programming Language :: Python :: 3.11
Requires-Python: >=3.8
